setup.cfg
setup.py
ex_bushra/ex_bushra.py
ex_bushra.egg-info/PKG-INFO
ex_bushra.egg-info/SOURCES.txt
ex_bushra.egg-info/dependency_links.txt
ex_bushra.egg-info/not-zip-safe
ex_bushra.egg-info/top_level.txt