Metadata-Version: 2.1
Name: ex-bushra
Version: 0.0
Summary: ex_bushra
Author-email: ilapronin0700@gmail.com
